my_module/__init__.py
my_module/my_function.py
ilaevmodule-0.2.0.dist-info/METADATA
ilaevmodule-0.2.0.dist-info/WHEEL
ilaevmodule-0.2.0.dist-info/top_level.txt
ilaevmodule-0.2.0.dist-info/RECORD
